lucier/__init__.py
lucier/core.py
lucier/utils.py
lucier-0.0.2.dist-info/METADATA
lucier-0.0.2.dist-info/WHEEL
lucier-0.0.2.dist-info/top_level.txt
lucier-0.0.2.dist-info/RECORD
