Metadata-Version: 2.1
Name: lucier
Version: 0.0.2
Summary: Sequence MIDI messages using a Flask-style interface.
Home-page: https://github.com/jacoblurye/lucier
Author: Jacob Lurye
License: UNKNOWN
Platform: UNKNOWN
Classifier: Programming Language :: Python :: 3
Classifier: License :: OSI Approved :: MIT License
Classifier: Operating System :: OS Independent
Requires-Python: >=3.6
Requires-Dist: mido (==1.2.9)
Requires-Dist: python-rtmidi (==1.4.6)
